clip_mosaic/__init__.py
clip_mosaic/main.py
clip_mosaic-0.1.0.dist-info/METADATA
clip_mosaic-0.1.0.dist-info/WHEEL
clip_mosaic-0.1.0.dist-info/RECORD
