Metadata-Version: 2.1
Name: clip-mosaic
Version: 0.1.0
Summary: Clip & Mosaic multiple TIFF Images with shapefiles.
Author: zheuziihau
Author-email: 812325695@qq.com
Requires-Python: >=3.10,<4.0
Classifier: Programming Language :: Python :: 3
Classifier: Programming Language :: Python :: 3.10
Classifier: Programming Language :: Python :: 3.11
Classifier: Programming Language :: Python :: 3.12
Requires-Dist: geopandas
Requires-Dist: rasterio
